cs/app/mklinks.py
cs_app_mklinks-20250530.dist-info/entry_points.txt
cs_app_mklinks-20250530.dist-info/WHEEL
cs_app_mklinks-20250530.dist-info/METADATA
cs_app_mklinks-20250530.dist-info/RECORD
